{
  "lastUpdated": "2026-02-20T06:52:08.406Z",
  "events": [
    {
      "date": "2026-02-21",
      "title": "Acting Technique and Stagecraft with Imogen Palmer",
      "venue": "Bristol Improv Theatre",
      "time": "10:00–17:00",
      "type": "workshop",
      "url": "https://improvtheatre.co.uk/upcoming-show/acting-technique-and-stagecraft-with-imogen-palmer-2/",
      "description": ""
    },
    {
      "date": "2026-02-21",
      "title": "Improv Taster Session",
      "venue": "Bristol Improv Theatre",
      "time": "14:00–16:00",
      "type": "drop-in",
      "url": "https://improvtheatre.co.uk/upcoming-show/improv-taster-session-3-2-5/",
      "description": ""
    },
    {
      "date": "2026-02-22",
      "title": "Grounding In Game",
      "venue": "The Stag & Hounds",
      "time": "12:00–15:00",
      "type": "workshop",
      "url": "https://www.eventbrite.com/checkout-external?eid=1981162485325",
      "description": ""
    },
    {
      "date": "2026-02-23",
      "title": "Lunchtime Improv with Rebecca MacMillan",
      "venue": "Bristol Improv Theatre",
      "time": "13:00–14:30",
      "type": "drop-in",
      "url": "https://improvtheatre.co.uk/upcoming-show/lunchtime-improv-with-rebecca-macmillan-2-2/2026-02-23/",
      "description": ""
    },
    {
      "date": "2026-02-23",
      "title": "Level 3: Performing Improv – Telling Stories",
      "venue": "Bristol Improv Theatre",
      "time": "18:30–21:00",
      "type": "workshop",
      "url": "https://improvtheatre.co.uk/upcoming-show/level-3-performing-improv-telling-stories-2/",
      "description": ""
    },
    {
      "date": "2026-02-23",
      "title": "Level 1: Discovering Improv",
      "venue": "Bristol Improv Theatre",
      "time": "18:30–21:00",
      "type": "workshop",
      "url": "https://improvtheatre.co.uk/upcoming-show/level-1-discovering-improv-4/",
      "description": ""
    },
    {
      "date": "2026-02-23",
      "title": "Improv Drop-ins",
      "venue": "Bristol Improv Theatre",
      "time": "19:00–21:00",
      "type": "drop-in",
      "url": "https://improvtheatre.co.uk/upcoming-show/improv-drop-ins-3-2-2-3-3-2/2026-02-23/",
      "description": ""
    },
    {
      "date": "2026-02-23",
      "title": "Closer Each Day: The Improvised Soap Opera",
      "venue": "Wardrobe Theatre",
      "time": "19:30",
      "type": "show",
      "url": "https://thewardrobetheatre.com/shows/closer-each-day/",
      "description": ""
    },
    {
      "date": "2026-02-24",
      "title": "Level 2: Intro to Performing Improv",
      "venue": "Bristol Improv Theatre",
      "time": "18:30–21:00",
      "type": "workshop",
      "url": "https://improvtheatre.co.uk/upcoming-show/level-2-intro-to-performing-improv-4/",
      "description": ""
    },
    {
      "date": "2026-02-24",
      "title": "Performing Improv Level 4: Developing Characters",
      "venue": "Bristol Improv Theatre",
      "time": "18:30–21:00",
      "type": "workshop",
      "url": "https://improvtheatre.co.uk/upcoming-show/performing-improv-level-4-developing-characters/",
      "description": ""
    },
    {
      "date": "2026-02-25",
      "title": "Level 1: Discovering Improv",
      "venue": "Bristol Improv Theatre",
      "time": "18:30–21:00",
      "type": "workshop",
      "url": "https://improvtheatre.co.uk/upcoming-show/level-1-discovering-improv-5/",
      "description": ""
    },
    {
      "date": "2026-02-25",
      "title": "Improv to Sketch with Maria Peters",
      "venue": "Bristol Improv Theatre",
      "time": "18:30–21:30",
      "type": "workshop",
      "url": "https://improvtheatre.co.uk/upcoming-show/improv-to-sketch-with-maria-peters/",
      "description": ""
    },
    {
      "date": "2026-02-25",
      "title": "Tales From The Wasteland: Post-Apocalyptic Improv",
      "venue": "Hen & Chicken",
      "time": "20:00",
      "type": "show",
      "url": "https://www.headfirstbristol.co.uk/whats-on/hen-and-chicken/wed-25-feb-tales-from-the-wasteland-post-apocalyptic-improv-142254",
      "description": ""
    },
    {
      "date": "2026-02-26",
      "title": "Bristol Longform Takeover",
      "venue": "Bristol Improv Theatre",
      "time": "19:30–21:30",
      "type": "show",
      "url": "https://improvtheatre.co.uk/upcoming-show/bristol-longform-takeover-feb-2026/",
      "description": ""
    },
    {
      "date": "2026-02-26",
      "title": "My Date with Pierce Brosnan feat. The Brothers Grin",
      "venue": "PRSC",
      "time": "19:30",
      "type": "show",
      "url": "https://www.headfirstbristol.co.uk/whats-on/prsc/thu-26-feb-my-date-with-pierce-brosnan-feat-the-brothers-grin-144634",
      "description": ""
    },
    {
      "date": "2026-02-27",
      "title": "This Is Your Musical",
      "venue": "Bristol Improv Theatre",
      "time": "20:00–22:00",
      "type": "show",
      "url": "https://improvtheatre.co.uk/upcoming-show/this-is-your-musical-2026/2026-02-27/",
      "description": ""
    },
    {
      "date": "2026-02-28",
      "title": "The Improv Spotlight",
      "venue": "PRSC",
      "time": "19:00–21:30",
      "type": "show",
      "url": "https://prsc.org.uk/event/the-improv-spotlight-13/",
      "description": ""
    },
    {
      "date": "2026-02-28",
      "title": "The Antics Joke Show #100 Ft. The Mayor and His Daughter",
      "venue": "Bristol Improv Theatre",
      "time": "19:30–22:30",
      "type": "show",
      "url": "https://improvtheatre.co.uk/upcoming-show/the-antics-joke-show-100-ft-mayor-and-daughter/",
      "description": ""
    },
    {
      "date": "2026-03-01",
      "title": "ZineZilla Exhibition Preview",
      "venue": "Bristol Improv Theatre",
      "time": "17:00–21:30",
      "type": "show",
      "url": "https://improvtheatre.co.uk/upcoming-show/zinezilla-exhibition-preview/",
      "description": ""
    },
    {
      "date": "2026-03-02",
      "title": "Lunchtime Improv with Rebecca MacMillan",
      "venue": "Bristol Improv Theatre",
      "time": "13:00–14:30",
      "type": "drop-in",
      "url": "https://improvtheatre.co.uk/upcoming-show/lunchtime-improv-with-rebecca-macmillan-2-2/2026-03-02/",
      "description": ""
    },
    {
      "date": "2026-03-02",
      "title": "Improv Drop-ins",
      "venue": "Bristol Improv Theatre",
      "time": "19:00–21:00",
      "type": "drop-in",
      "url": "https://improvtheatre.co.uk/upcoming-show/improv-drop-ins-3-2-2-3-3-2/2026-03-02/",
      "description": ""
    },
    {
      "date": "2026-03-04",
      "title": "Being a Difficult Woman* at Work: Full day Workshop",
      "venue": "Bristol Improv Theatre",
      "time": "09:30–16:00",
      "type": "workshop",
      "url": "https://improvtheatre.co.uk/upcoming-show/being-a-difficult-woman-at-work-full-day-workshop/",
      "description": ""
    },
    {
      "date": "2026-03-05",
      "title": "Improv Jam & Social",
      "venue": "Bristol Improv Theatre",
      "time": "19:30–21:30",
      "type": "jam",
      "url": "https://improvtheatre.co.uk/upcoming-show/improv-jam-social-2026/2026-03-05/",
      "description": ""
    },
    {
      "date": "2026-03-05",
      "title": "'Title Goes Here' an Improv Comedy",
      "venue": "Alma Tavern Theatre",
      "time": "20:00",
      "type": "show",
      "url": "https://www.tickettailor.com/events/almatheatrecompany/2010679",
      "description": ""
    },
    {
      "date": "2026-03-06",
      "title": "Improv for Actors with Maria Peters",
      "venue": "Bristol Improv Theatre",
      "time": "18:30",
      "type": "workshop",
      "url": "https://improvtheatre.co.uk/upcoming-show/improv-for-actors-with-maria-peters/",
      "description": ""
    },
    {
      "date": "2026-03-06",
      "title": "The Bish Bosh Bash: The Improvised Game Show",
      "venue": "Bristol Improv Theatre",
      "time": "19:30–21:30",
      "type": "show",
      "url": "https://improvtheatre.co.uk/upcoming-show/the-bish-bosh-bash-the-improvised-game-show-2026/2026-03-06/",
      "description": ""
    },
    {
      "date": "2026-03-07",
      "title": "Improv Taster Session",
      "venue": "Bristol Improv Theatre",
      "time": "14:00–16:00",
      "type": "drop-in",
      "url": "https://improvtheatre.co.uk/upcoming-show/improv-taster-session-3-2/2026-03-07/",
      "description": ""
    },
    {
      "date": "2026-03-08",
      "title": "International Women’s Day Improv Jam",
      "venue": "Bristol Improv Theatre",
      "time": "19:00–21:00",
      "type": "jam",
      "url": "https://improvtheatre.co.uk/upcoming-show/international-womens-day-improv-jam/",
      "description": ""
    },
    {
      "date": "2026-03-09",
      "title": "Lunchtime Improv with Rebecca MacMillan",
      "venue": "Bristol Improv Theatre",
      "time": "13:00–14:30",
      "type": "drop-in",
      "url": "https://improvtheatre.co.uk/upcoming-show/lunchtime-improv-with-rebecca-macmillan-2-2/2026-03-09/",
      "description": ""
    },
    {
      "date": "2026-03-09",
      "title": "Improv Drop-ins",
      "venue": "Bristol Improv Theatre",
      "time": "19:00–21:00",
      "type": "drop-in",
      "url": "https://improvtheatre.co.uk/upcoming-show/improv-drop-ins-3-2-2-3-3-2/2026-03-09/",
      "description": ""
    },
    {
      "date": "2026-03-09",
      "title": "Closer Each Day: The Improvised Soap Opera",
      "venue": "Wardrobe Theatre",
      "time": "19:30",
      "type": "show",
      "url": "https://thewardrobetheatre.com/shows/closer-each-day/",
      "description": ""
    },
    {
      "date": "2026-03-11",
      "title": "Wednesday Night Improv: March Triple Bill",
      "venue": "Hen & Chicken",
      "time": "19:30",
      "type": "show",
      "url": "https://www.headfirstbristol.co.uk/whats-on/hen-and-chicken/wed-11-mar-wednesday-night-improv-march-triple-bill-146295",
      "description": ""
    },
    {
      "date": "2026-03-12",
      "title": "The Drag Dungeoneers",
      "venue": "Bristol Improv Theatre",
      "time": "19:30–22:00",
      "type": "show",
      "url": "https://improvtheatre.co.uk/upcoming-show/the-drag-dungeoneers-mar26/",
      "description": ""
    },
    {
      "date": "2026-03-13",
      "title": "In The Cards",
      "venue": "Bristol Improv Theatre",
      "time": "19:30–21:30",
      "type": "show",
      "url": "https://improvtheatre.co.uk/upcoming-show/in-the-cards-mar-26/",
      "description": ""
    },
    {
      "date": "2026-03-14",
      "title": "Introduction to Meisner Technique with Greg Shewring",
      "venue": "Bristol Improv Theatre",
      "time": "10:00–17:00",
      "type": "workshop",
      "url": "https://improvtheatre.co.uk/upcoming-show/introduction-to-meisner-technique-with-greg-shewring/",
      "description": ""
    },
    {
      "date": "2026-03-14",
      "title": "LGBTQ+ Improv Drop-In",
      "venue": "Bristol Improv Theatre",
      "time": "14:00–16:00",
      "type": "drop-in",
      "url": "https://improvtheatre.co.uk/upcoming-show/lgbtq-improv-drop-in-3-2/2026-03-14/",
      "description": ""
    },
    {
      "date": "2026-03-14",
      "title": "Black Box Cinema Club Presents: The Princess Bride",
      "venue": "Bristol Improv Theatre",
      "time": "19:30–21:30",
      "type": "show",
      "url": "https://improvtheatre.co.uk/upcoming-show/black-box-cinema-club-presents-the-princess-bride/",
      "description": ""
    },
    {
      "date": "2026-03-15",
      "title": "Stand up Comedy in broken English • Victor Patrascan in Bristol",
      "venue": "The Bristol Improv Theatre",
      "time": "17:00–18:30",
      "type": "show",
      "url": "https://www.eventbrite.com/checkout-external?eid=1980871509007",
      "description": ""
    },
    {
      "date": "2026-03-16",
      "title": "Lunchtime Improv with Rebecca MacMillan",
      "venue": "Bristol Improv Theatre",
      "time": "13:00–14:30",
      "type": "drop-in",
      "url": "https://improvtheatre.co.uk/upcoming-show/lunchtime-improv-with-rebecca-macmillan-2-2/2026-03-16/",
      "description": ""
    },
    {
      "date": "2026-03-16",
      "title": "Improv Drop-ins",
      "venue": "Bristol Improv Theatre",
      "time": "19:00–21:00",
      "type": "drop-in",
      "url": "https://improvtheatre.co.uk/upcoming-show/improv-drop-ins-3-2-2-3-3-2/2026-03-16/",
      "description": ""
    },
    {
      "date": "2026-03-18",
      "title": "The Improv Variety Show",
      "venue": "Loco Klub",
      "time": "19:30",
      "type": "show",
      "url": "https://www.headfirstbristol.co.uk/whats-on/loco-klub/wed-18-mar-the-improv-variety-show-147359",
      "description": ""
    },
    {
      "date": "2026-03-19",
      "title": "FREE Breathwork for Stress Release",
      "venue": "Bristol Improv Theatre",
      "time": "18:00–19:30",
      "type": "show",
      "url": "https://www.eventbrite.com/checkout-external?eid=1982185144125",
      "description": ""
    },
    {
      "date": "2026-03-19",
      "title": "Breathwork for Stress Release – Free Session",
      "venue": "Bristol Improv Theatre",
      "time": "18:00–19:30",
      "type": "show",
      "url": "https://improvtheatre.co.uk/upcoming-show/breathwork-for-stress-release-free-session/",
      "description": ""
    },
    {
      "date": "2026-03-20",
      "title": "Blame of Thrones - an improv comedy show",
      "venue": "PRSC",
      "time": "19:30",
      "type": "show",
      "url": "https://www.headfirstbristol.co.uk/whats-on/prsc/fri-20-mar-blame-of-thrones-an-improv-comedy-show-146311",
      "description": ""
    },
    {
      "date": "2026-03-20",
      "title": "This Is Your Musical",
      "venue": "Bristol Improv Theatre",
      "time": "20:00–22:00",
      "type": "show",
      "url": "https://improvtheatre.co.uk/upcoming-show/this-is-your-musical-2026/2026-03-20/",
      "description": ""
    },
    {
      "date": "2026-03-21",
      "title": "Making Interactive Theatre with Dylan Lowena",
      "venue": "Bristol Improv Theatre",
      "time": "10:00–17:00",
      "type": "workshop",
      "url": "https://improvtheatre.co.uk/upcoming-show/making-interactive-theatre-with-dylan-lowena/",
      "description": ""
    },
    {
      "date": "2026-03-21",
      "title": "Improv Taster Session",
      "venue": "Bristol Improv Theatre",
      "time": "14:00–16:00",
      "type": "drop-in",
      "url": "https://improvtheatre.co.uk/upcoming-show/improv-taster-session-3-2-2/",
      "description": ""
    },
    {
      "date": "2026-03-21",
      "title": "The Improv Spotlight: Anniversary Special!",
      "venue": "PRSC",
      "time": "19:00–21:30",
      "type": "show",
      "url": "https://prsc.org.uk/event/the-improv-spotlight-anniversary-special/",
      "description": ""
    },
    {
      "date": "2026-03-23",
      "title": "Lunchtime Improv with Rebecca MacMillan",
      "venue": "Bristol Improv Theatre",
      "time": "13:00–14:30",
      "type": "drop-in",
      "url": "https://improvtheatre.co.uk/upcoming-show/lunchtime-improv-with-rebecca-macmillan-2-2/2026-03-23/",
      "description": ""
    },
    {
      "date": "2026-03-23",
      "title": "Improv Drop-ins",
      "venue": "Bristol Improv Theatre",
      "time": "19:00–21:00",
      "type": "drop-in",
      "url": "https://improvtheatre.co.uk/upcoming-show/improv-drop-ins-3-2-2-3-3-2/2026-03-23/",
      "description": ""
    },
    {
      "date": "2026-03-23",
      "title": "Closer Each Day: The Improvised Soap Opera",
      "venue": "Wardrobe Theatre",
      "time": "19:30",
      "type": "show",
      "url": "https://thewardrobetheatre.com/shows/closer-each-day/",
      "description": ""
    },
    {
      "date": "2026-03-25",
      "title": "Tales from the Wasteland",
      "venue": "Alma Tavern Theatre",
      "time": "20:00–22:00",
      "type": "show",
      "url": "https://www.tickettailor.com/events/almatheatrecompany/2018412",
      "description": ""
    },
    {
      "date": "2026-03-27",
      "title": "Predicted: A Wickedly Good Parody",
      "venue": "Bristol Improv Theatre",
      "time": "19:30–21:30",
      "type": "show",
      "url": "https://improvtheatre.co.uk/upcoming-show/predicted-a-wickedly-good-parody/",
      "description": ""
    },
    {
      "date": "2026-03-28",
      "title": "The Improv Lab",
      "venue": "Bristol Improv Theatre",
      "time": "14:00–17:00",
      "type": "jam",
      "url": "https://improvtheatre.co.uk/upcoming-show/the-improv-lab-march-2026/",
      "description": ""
    },
    {
      "date": "2026-03-28",
      "title": "The Antics Joke Show Improv Special Ft Degrees of Error",
      "venue": "Bristol Improv Theatre",
      "time": "19:30–22:30",
      "type": "show",
      "url": "https://improvtheatre.co.uk/upcoming-show/the-antics-joke-show-ft-degrees-of-error/",
      "description": ""
    },
    {
      "date": "2026-03-30",
      "title": "Lunchtime Improv with Rebecca MacMillan",
      "venue": "Bristol Improv Theatre",
      "time": "14:00–15:30",
      "type": "drop-in",
      "url": "https://improvtheatre.co.uk/upcoming-show/lunchtime-improv-with-rebecca-macmillan-2-2/2026-03-30/",
      "description": ""
    },
    {
      "date": "2026-03-30",
      "title": "Improv Drop-ins",
      "venue": "Bristol Improv Theatre",
      "time": "20:00–22:00",
      "type": "drop-in",
      "url": "https://improvtheatre.co.uk/upcoming-show/improv-drop-ins-3-2-2-3-3-2/2026-03-30/",
      "description": ""
    },
    {
      "date": "2026-04-02",
      "title": "Improv Jam & Social",
      "venue": "Bristol Improv Theatre",
      "time": "20:30–22:30",
      "type": "jam",
      "url": "https://improvtheatre.co.uk/upcoming-show/improv-jam-social-2026/2026-04-02/",
      "description": ""
    },
    {
      "date": "2026-04-03",
      "title": "The Bish Bosh Bash: The Improvised Game Show",
      "venue": "Bristol Improv Theatre",
      "time": "20:30–22:30",
      "type": "show",
      "url": "https://improvtheatre.co.uk/upcoming-show/the-bish-bosh-bash-the-improvised-game-show-2026/2026-04-03/",
      "description": ""
    },
    {
      "date": "2026-04-04",
      "title": "Improv Taster Session",
      "venue": "Bristol Improv Theatre",
      "time": "15:00–17:00",
      "type": "drop-in",
      "url": "https://improvtheatre.co.uk/upcoming-show/improv-taster-session-3-2/2026-04-04/",
      "description": ""
    },
    {
      "date": "2026-04-06",
      "title": "Lunchtime Improv with Rebecca MacMillan",
      "venue": "Bristol Improv Theatre",
      "time": "14:00–15:30",
      "type": "drop-in",
      "url": "https://improvtheatre.co.uk/upcoming-show/lunchtime-improv-with-rebecca-macmillan-2-2/2026-04-06/",
      "description": ""
    },
    {
      "date": "2026-04-06",
      "title": "Improv Drop-ins",
      "venue": "Bristol Improv Theatre",
      "time": "20:00–22:00",
      "type": "drop-in",
      "url": "https://improvtheatre.co.uk/upcoming-show/improv-drop-ins-3-2-2-3-3-2/2026-04-06/",
      "description": ""
    },
    {
      "date": "2026-04-06",
      "title": "Closer Each Day: The Improvised Soap Opera",
      "venue": "Wardrobe Theatre",
      "time": "20:30",
      "type": "show",
      "url": "https://thewardrobetheatre.com/shows/closer-each-day/",
      "description": ""
    },
    {
      "date": "2026-04-08",
      "title": "Wednesday Night Improv: April Triple Bill",
      "venue": "Hen & Chicken",
      "time": "20:30",
      "type": "show",
      "url": "https://www.headfirstbristol.co.uk/whats-on/hen-and-chicken/wed-8-apr-wednesday-night-improv-april-triple-bill-146296",
      "description": ""
    },
    {
      "date": "2026-04-09",
      "title": "The Drag Dungeoneers",
      "venue": "Bristol Improv Theatre",
      "time": "20:30–23:00",
      "type": "show",
      "url": "https://improvtheatre.co.uk/upcoming-show/the-drag-dungeoneers-april-2026/",
      "description": ""
    },
    {
      "date": "2026-04-10",
      "title": "Do The Right Scene present: Walworth Road",
      "venue": "Bristol Improv Theatre",
      "time": "20:30–22:30",
      "type": "show",
      "url": "https://improvtheatre.co.uk/upcoming-show/do-the-right-scene-apr-2026/",
      "description": ""
    },
    {
      "date": "2026-04-11",
      "title": "Instant Wit!",
      "venue": "Alma Tavern Theatre",
      "time": "20:00–22:00",
      "type": "show",
      "url": "https://www.tickettailor.com/events/almatheatrecompany/1988765",
      "description": ""
    },
    {
      "date": "2026-04-13",
      "title": "Lunchtime Improv with Rebecca MacMillan",
      "venue": "Bristol Improv Theatre",
      "time": "14:00–15:30",
      "type": "drop-in",
      "url": "https://improvtheatre.co.uk/upcoming-show/lunchtime-improv-with-rebecca-macmillan-2-2/2026-04-13/",
      "description": ""
    },
    {
      "date": "2026-04-13",
      "title": "Performing Improv Level 1: Making a Scene",
      "venue": "Bristol Improv Theatre",
      "time": "19:30–22:00",
      "type": "workshop",
      "url": "https://improvtheatre.co.uk/upcoming-show/performing-improv-level-1-making-a-scene-2/",
      "description": ""
    },
    {
      "date": "2026-04-13",
      "title": "Level 2: Intro to Performing Improv",
      "venue": "Bristol Improv Theatre",
      "time": "19:30–22:00",
      "type": "workshop",
      "url": "https://improvtheatre.co.uk/upcoming-show/level-2-intro-to-performing-improv-5/",
      "description": ""
    },
    {
      "date": "2026-04-13",
      "title": "Performing Improv Level 3: Making a Scene",
      "venue": "Bristol Improv Theatre",
      "time": "19:30–22:00",
      "type": "workshop",
      "url": "https://improvtheatre.co.uk/upcoming-show/performing-improv-level-1-making-a-scene-2/",
      "description": ""
    },
    {
      "date": "2026-04-13",
      "title": "Improv Drop-ins",
      "venue": "Bristol Improv Theatre",
      "time": "20:00–22:00",
      "type": "drop-in",
      "url": "https://improvtheatre.co.uk/upcoming-show/improv-drop-ins-3-2-2-3-3-2/2026-04-13/",
      "description": ""
    },
    {
      "date": "2026-04-14",
      "title": "Level 1: Discovering Improv",
      "venue": "Bristol Improv Theatre",
      "time": "19:30–22:00",
      "type": "workshop",
      "url": "https://improvtheatre.co.uk/upcoming-show/level-1-discovering-improv-6/",
      "description": ""
    },
    {
      "date": "2026-04-14",
      "title": "Level 4: Performing Improv – Scenes and Songs",
      "venue": "Bristol Improv Theatre",
      "time": "19:30–22:00",
      "type": "workshop",
      "url": "https://improvtheatre.co.uk/upcoming-show/performing-improv-level-2-scenes-and-songs/",
      "description": ""
    },
    {
      "date": "2026-04-15",
      "title": "Level 1: Discovering Improv",
      "venue": "Bristol Improv Theatre",
      "time": "19:30–22:00",
      "type": "workshop",
      "url": "https://improvtheatre.co.uk/upcoming-show/level-1-discovering-improv-7/",
      "description": ""
    },
    {
      "date": "2026-04-17",
      "title": "Impromptu Shakespeare",
      "venue": "Wardrobe Theatre",
      "time": "20:30",
      "type": "show",
      "url": "https://thewardrobetheatre.com/shows/impromptu-shakespeare/",
      "description": ""
    },
    {
      "date": "2026-04-17",
      "title": "This Is Your Musical",
      "venue": "Bristol Improv Theatre",
      "time": "21:00–23:00",
      "type": "show",
      "url": "https://improvtheatre.co.uk/upcoming-show/this-is-your-musical-2026/2026-04-17/",
      "description": ""
    },
    {
      "date": "2026-04-18",
      "title": "Improv Taster Session",
      "venue": "Bristol Improv Theatre",
      "time": "15:00–17:00",
      "type": "drop-in",
      "url": "https://improvtheatre.co.uk/upcoming-show/improv-taster-session-3-2-3/",
      "description": ""
    },
    {
      "date": "2026-04-18",
      "title": "Impromptu Shakespeare",
      "venue": "Wardrobe Theatre",
      "time": "20:30",
      "type": "show",
      "url": "https://thewardrobetheatre.com/shows/impromptu-shakespeare/",
      "description": ""
    },
    {
      "date": "2026-04-19",
      "title": "Impromptu Shakespeare",
      "venue": "Wardrobe Theatre",
      "time": "20:00",
      "type": "show",
      "url": "https://thewardrobetheatre.com/shows/impromptu-shakespeare/",
      "description": ""
    },
    {
      "date": "2026-04-20",
      "title": "Lunchtime Improv with Rebecca MacMillan",
      "venue": "Bristol Improv Theatre",
      "time": "14:00–15:30",
      "type": "drop-in",
      "url": "https://improvtheatre.co.uk/upcoming-show/lunchtime-improv-with-rebecca-macmillan-2-2/2026-04-20/",
      "description": ""
    },
    {
      "date": "2026-04-20",
      "title": "Improv Drop-ins",
      "venue": "Bristol Improv Theatre",
      "time": "20:00–22:00",
      "type": "drop-in",
      "url": "https://improvtheatre.co.uk/upcoming-show/improv-drop-ins-3-2-2-3-3-2/2026-04-20/",
      "description": ""
    },
    {
      "date": "2026-04-20",
      "title": "Closer Each Day: The Improvised Soap Opera",
      "venue": "Wardrobe Theatre",
      "time": "20:30",
      "type": "show",
      "url": "https://thewardrobetheatre.com/shows/closer-each-day/",
      "description": ""
    },
    {
      "date": "2026-04-23",
      "title": "Unscripted Players Big Spring Show",
      "venue": "Bristol Improv Theatre",
      "time": "20:30–23:30",
      "type": "show",
      "url": "https://improvtheatre.co.uk/upcoming-show/unscripted-players-big-spring-show-2026/2026-04-23/",
      "description": ""
    },
    {
      "date": "2026-04-24",
      "title": "Unscripted Players Big Spring Show",
      "venue": "Bristol Improv Theatre",
      "time": "20:30–23:30",
      "type": "show",
      "url": "https://improvtheatre.co.uk/upcoming-show/unscripted-players-big-spring-show-2026/2026-04-24/",
      "description": ""
    },
    {
      "date": "2026-04-25",
      "title": "Unscripted Players Big Spring Show",
      "venue": "Bristol Improv Theatre",
      "time": "20:30–23:30",
      "type": "show",
      "url": "https://improvtheatre.co.uk/upcoming-show/unscripted-players-big-spring-show-2026/2026-04-25/",
      "description": ""
    },
    {
      "date": "2026-04-27",
      "title": "Lunchtime Improv with Rebecca MacMillan",
      "venue": "Bristol Improv Theatre",
      "time": "14:00–15:30",
      "type": "drop-in",
      "url": "https://improvtheatre.co.uk/upcoming-show/lunchtime-improv-with-rebecca-macmillan-2-2/2026-04-27/",
      "description": ""
    },
    {
      "date": "2026-04-27",
      "title": "Improv Drop-ins",
      "venue": "Bristol Improv Theatre",
      "time": "20:00–22:00",
      "type": "drop-in",
      "url": "https://improvtheatre.co.uk/upcoming-show/improv-drop-ins-3-2-2-3-3-2/2026-04-27/",
      "description": ""
    },
    {
      "date": "2026-05-01",
      "title": "The Bish Bosh Bash: The Improvised Game Show",
      "venue": "Bristol Improv Theatre",
      "time": "20:30–22:30",
      "type": "show",
      "url": "https://improvtheatre.co.uk/upcoming-show/the-bish-bosh-bash-the-improvised-game-show-2026/2026-05-01/",
      "description": ""
    },
    {
      "date": "2026-05-02",
      "title": "Improv Taster Session",
      "venue": "Bristol Improv Theatre",
      "time": "15:00–17:00",
      "type": "drop-in",
      "url": "https://improvtheatre.co.uk/upcoming-show/improv-taster-session-3-2/2026-05-02/",
      "description": ""
    },
    {
      "date": "2026-05-02",
      "title": "LGBTQ+ Improv Drop-In",
      "venue": "Bristol Improv Theatre",
      "time": "15:00–17:00",
      "type": "drop-in",
      "url": "https://improvtheatre.co.uk/upcoming-show/lgbtq-improv-drop-in-3-2/2026-05-02/",
      "description": ""
    },
    {
      "date": "2026-05-04",
      "title": "Lunchtime Improv with Rebecca MacMillan",
      "venue": "Bristol Improv Theatre",
      "time": "14:00–15:30",
      "type": "drop-in",
      "url": "https://improvtheatre.co.uk/upcoming-show/lunchtime-improv-with-rebecca-macmillan-2-2/2026-05-04/",
      "description": ""
    },
    {
      "date": "2026-05-04",
      "title": "Improv Drop-ins",
      "venue": "Bristol Improv Theatre",
      "time": "20:00–22:00",
      "type": "drop-in",
      "url": "https://improvtheatre.co.uk/upcoming-show/improv-drop-ins-3-2-2-3-3-2/2026-05-04/",
      "description": ""
    },
    {
      "date": "2026-05-04",
      "title": "Closer Each Day: The Improvised Soap Opera",
      "venue": "Wardrobe Theatre",
      "time": "20:30",
      "type": "show",
      "url": "https://thewardrobetheatre.com/shows/closer-each-day/",
      "description": ""
    },
    {
      "date": "2026-05-11",
      "title": "Lunchtime Improv with Rebecca MacMillan",
      "venue": "Bristol Improv Theatre",
      "time": "14:00–15:30",
      "type": "drop-in",
      "url": "https://improvtheatre.co.uk/upcoming-show/lunchtime-improv-with-rebecca-macmillan-2-2/2026-05-11/",
      "description": ""
    },
    {
      "date": "2026-05-11",
      "title": "Improv Drop-ins",
      "venue": "Bristol Improv Theatre",
      "time": "20:00–22:00",
      "type": "drop-in",
      "url": "https://improvtheatre.co.uk/upcoming-show/improv-drop-ins-3-2-2-3-3-2/2026-05-11/",
      "description": ""
    },
    {
      "date": "2026-05-14",
      "title": "The Drag Dungeoneers",
      "venue": "Bristol Improv Theatre",
      "time": "20:30–23:00",
      "type": "show",
      "url": "https://improvtheatre.co.uk/upcoming-show/the-drag-dungeoneers-may-2026/",
      "description": ""
    },
    {
      "date": "2026-05-15",
      "title": "This Is Your Musical",
      "venue": "Bristol Improv Theatre",
      "time": "21:00–23:00",
      "type": "show",
      "url": "https://improvtheatre.co.uk/upcoming-show/this-is-your-musical-2026/2026-05-15/",
      "description": ""
    },
    {
      "date": "2026-05-16",
      "title": "Improv Taster Session",
      "venue": "Bristol Improv Theatre",
      "time": "15:00–17:00",
      "type": "drop-in",
      "url": "https://improvtheatre.co.uk/upcoming-show/improv-taster-session-3-2/2026-05-16/",
      "description": ""
    },
    {
      "date": "2026-05-18",
      "title": "Lunchtime Improv with Rebecca MacMillan",
      "venue": "Bristol Improv Theatre",
      "time": "14:00–15:30",
      "type": "drop-in",
      "url": "https://improvtheatre.co.uk/upcoming-show/lunchtime-improv-with-rebecca-macmillan-2-2/2026-05-18/",
      "description": ""
    },
    {
      "date": "2026-05-18",
      "title": "Improv Drop-ins",
      "venue": "Bristol Improv Theatre",
      "time": "20:00–22:00",
      "type": "drop-in",
      "url": "https://improvtheatre.co.uk/upcoming-show/improv-drop-ins-3-2-2-3-3-2/2026-05-18/",
      "description": ""
    },
    {
      "date": "2026-05-18",
      "title": "Closer Each Day: The Improvised Soap Opera",
      "venue": "Wardrobe Theatre",
      "time": "20:30",
      "type": "show",
      "url": "https://thewardrobetheatre.com/shows/closer-each-day/",
      "description": ""
    },
    {
      "date": "2026-05-25",
      "title": "Lunchtime Improv with Rebecca MacMillan",
      "venue": "Bristol Improv Theatre",
      "time": "14:00–15:30",
      "type": "drop-in",
      "url": "https://improvtheatre.co.uk/upcoming-show/lunchtime-improv-with-rebecca-macmillan-2-2/2026-05-25/",
      "description": ""
    },
    {
      "date": "2026-05-25",
      "title": "Improv Drop-ins",
      "venue": "Bristol Improv Theatre",
      "time": "20:00–22:00",
      "type": "drop-in",
      "url": "https://improvtheatre.co.uk/upcoming-show/improv-drop-ins-3-2-2-3-3-2/2026-05-25/",
      "description": ""
    },
    {
      "date": "2026-05-25",
      "title": "Performing Improv Level1: Making a Scene Student Showcase",
      "venue": "Bristol Improv Theatre",
      "time": "20:30–22:00",
      "type": "show",
      "url": "https://improvtheatre.co.uk/upcoming-show/performing-improv-level1-making-a-scene-student-showcase-2/",
      "description": ""
    },
    {
      "date": "2026-05-26",
      "title": "Performing L2: Scenes and Songs Student Showcase",
      "venue": "Bristol Improv Theatre",
      "time": "20:30–22:00",
      "type": "show",
      "url": "https://improvtheatre.co.uk/upcoming-show/performing-l2-scenes-and-songs-student-showcase-2/",
      "description": ""
    },
    {
      "date": "2026-05-26",
      "title": "Performing Improv Level 4: Scenes and Songs Student Showcase",
      "venue": "Bristol Improv Theatre",
      "time": "20:30–22:00",
      "type": "show",
      "url": "https://improvtheatre.co.uk/upcoming-show/performing-l2-scenes-and-songs-student-showcase-2/",
      "description": ""
    },
    {
      "date": "2026-05-30",
      "title": "Instant Wit!",
      "venue": "Alma Tavern Theatre",
      "time": "20:00–22:00",
      "type": "show",
      "url": "https://www.tickettailor.com/events/almatheatrecompany/2021946",
      "description": ""
    },
    {
      "date": "2026-06-01",
      "title": "Lunchtime Improv with Rebecca MacMillan",
      "venue": "Bristol Improv Theatre",
      "time": "14:00–15:30",
      "type": "drop-in",
      "url": "https://improvtheatre.co.uk/upcoming-show/lunchtime-improv-with-rebecca-macmillan-2-2/2026-06-01/",
      "description": ""
    },
    {
      "date": "2026-06-01",
      "title": "Improv Drop-ins",
      "venue": "Bristol Improv Theatre",
      "time": "20:00–22:00",
      "type": "drop-in",
      "url": "https://improvtheatre.co.uk/upcoming-show/improv-drop-ins-3-2-2-3-3-2/2026-06-01/",
      "description": ""
    },
    {
      "date": "2026-06-01",
      "title": "Closer Each Day: The Improvised Soap Opera",
      "venue": "Wardrobe Theatre",
      "time": "20:30",
      "type": "show",
      "url": "https://thewardrobetheatre.com/shows/closer-each-day/",
      "description": ""
    },
    {
      "date": "2026-06-06",
      "title": "Improv Taster Session",
      "venue": "Bristol Improv Theatre",
      "time": "15:00–17:00",
      "type": "drop-in",
      "url": "https://improvtheatre.co.uk/upcoming-show/improv-taster-session-3-2/2026-06-06/",
      "description": ""
    },
    {
      "date": "2026-06-08",
      "title": "Lunchtime Improv with Rebecca MacMillan",
      "venue": "Bristol Improv Theatre",
      "time": "14:00–15:30",
      "type": "drop-in",
      "url": "https://improvtheatre.co.uk/upcoming-show/lunchtime-improv-with-rebecca-macmillan-2-2/2026-06-08/",
      "description": ""
    },
    {
      "date": "2026-06-08",
      "title": "Improv Drop-ins",
      "venue": "Bristol Improv Theatre",
      "time": "20:00–22:00",
      "type": "drop-in",
      "url": "https://improvtheatre.co.uk/upcoming-show/improv-drop-ins-3-2-2-3-3-2/2026-06-08/",
      "description": ""
    },
    {
      "date": "2026-06-10",
      "title": "Dropout Improv",
      "venue": "Bristol Beacon",
      "time": "20:30",
      "type": "show",
      "url": "https://bristolbeacon.org/whats-on/dropout-improv-plus-special-guests/",
      "description": ""
    },
    {
      "date": "2026-06-11",
      "title": "The Drag Dungeoneers",
      "venue": "Bristol Improv Theatre",
      "time": "20:30–23:00",
      "type": "show",
      "url": "https://improvtheatre.co.uk/upcoming-show/the-drag-dungeoneers-jun26/",
      "description": ""
    },
    {
      "date": "2026-06-15",
      "title": "Lunchtime Improv with Rebecca MacMillan",
      "venue": "Bristol Improv Theatre",
      "time": "14:00–15:30",
      "type": "drop-in",
      "url": "https://improvtheatre.co.uk/upcoming-show/lunchtime-improv-with-rebecca-macmillan-2-2/2026-06-15/",
      "description": ""
    },
    {
      "date": "2026-06-15",
      "title": "Improv Drop-ins",
      "venue": "Bristol Improv Theatre",
      "time": "20:00–22:00",
      "type": "drop-in",
      "url": "https://improvtheatre.co.uk/upcoming-show/improv-drop-ins-3-2-2-3-3-2/2026-06-15/",
      "description": ""
    },
    {
      "date": "2026-06-19",
      "title": "This Is Your Musical",
      "venue": "Bristol Improv Theatre",
      "time": "21:00–23:00",
      "type": "show",
      "url": "https://improvtheatre.co.uk/upcoming-show/this-is-your-musical-2026/2026-06-19/",
      "description": ""
    },
    {
      "date": "2026-06-20",
      "title": "Improv Taster Session",
      "venue": "Bristol Improv Theatre",
      "time": "15:00–17:00",
      "type": "drop-in",
      "url": "https://improvtheatre.co.uk/upcoming-show/improv-taster-session-3-2/2026-06-20/",
      "description": ""
    },
    {
      "date": "2026-06-22",
      "title": "Lunchtime Improv with Rebecca MacMillan",
      "venue": "Bristol Improv Theatre",
      "time": "14:00–15:30",
      "type": "drop-in",
      "url": "https://improvtheatre.co.uk/upcoming-show/lunchtime-improv-with-rebecca-macmillan-2-2/2026-06-22/",
      "description": ""
    },
    {
      "date": "2026-06-22",
      "title": "Improv Drop-ins",
      "venue": "Bristol Improv Theatre",
      "time": "20:00–22:00",
      "type": "drop-in",
      "url": "https://improvtheatre.co.uk/upcoming-show/improv-drop-ins-3-2-2-3-3-2/2026-06-22/",
      "description": ""
    },
    {
      "date": "2026-06-29",
      "title": "Lunchtime Improv with Rebecca MacMillan",
      "venue": "Bristol Improv Theatre",
      "time": "14:00–15:30",
      "type": "drop-in",
      "url": "https://improvtheatre.co.uk/upcoming-show/lunchtime-improv-with-rebecca-macmillan-2-2/2026-06-29/",
      "description": ""
    },
    {
      "date": "2026-06-29",
      "title": "Improv Drop-ins",
      "venue": "Bristol Improv Theatre",
      "time": "20:00–22:00",
      "type": "drop-in",
      "url": "https://improvtheatre.co.uk/upcoming-show/improv-drop-ins-3-2-2-3-3-2/2026-06-29/",
      "description": ""
    },
    {
      "date": "2026-07-03",
      "title": "The Bish Bosh Bash: The Improvised Game Show",
      "venue": "Bristol Improv Theatre",
      "time": "20:30–22:30",
      "type": "show",
      "url": "https://improvtheatre.co.uk/upcoming-show/the-bish-bosh-bash-the-improvised-game-show-2026/2026-07-03/",
      "description": ""
    },
    {
      "date": "2026-07-04",
      "title": "Improv Taster Session",
      "venue": "Bristol Improv Theatre",
      "time": "15:00–17:00",
      "type": "drop-in",
      "url": "https://improvtheatre.co.uk/upcoming-show/improv-taster-session-3-2/2026-07-04/",
      "description": ""
    },
    {
      "date": "2026-07-04",
      "title": "LGBTQ+ Improv Drop-In",
      "venue": "Bristol Improv Theatre",
      "time": "15:00–17:00",
      "type": "drop-in",
      "url": "https://improvtheatre.co.uk/upcoming-show/lgbtq-improv-drop-in-3-2/2026-07-04/",
      "description": ""
    },
    {
      "date": "2026-07-06",
      "title": "Lunchtime Improv with Rebecca MacMillan",
      "venue": "Bristol Improv Theatre",
      "time": "14:00–15:30",
      "type": "drop-in",
      "url": "https://improvtheatre.co.uk/upcoming-show/lunchtime-improv-with-rebecca-macmillan-2-2/2026-07-06/",
      "description": ""
    },
    {
      "date": "2026-07-06",
      "title": "Improv Drop-ins",
      "venue": "Bristol Improv Theatre",
      "time": "20:00–22:00",
      "type": "drop-in",
      "url": "https://improvtheatre.co.uk/upcoming-show/improv-drop-ins-3-2-2-3-3-2/2026-07-06/",
      "description": ""
    },
    {
      "date": "2026-07-10",
      "title": "Tales From The Wasteland: Pride Special",
      "venue": "The Folk House",
      "time": "21:00",
      "type": "show",
      "url": "https://www.headfirstbristol.co.uk/whats-on/the-folk-house/fri-10-jul-tales-from-the-wasteland-pride-special--147438",
      "description": ""
    },
    {
      "date": "2026-07-13",
      "title": "Lunchtime Improv with Rebecca MacMillan",
      "venue": "Bristol Improv Theatre",
      "time": "14:00–15:30",
      "type": "drop-in",
      "url": "https://improvtheatre.co.uk/upcoming-show/lunchtime-improv-with-rebecca-macmillan-2-2/2026-07-13/",
      "description": ""
    },
    {
      "date": "2026-07-13",
      "title": "Improv Drop-ins",
      "venue": "Bristol Improv Theatre",
      "time": "20:00–22:00",
      "type": "drop-in",
      "url": "https://improvtheatre.co.uk/upcoming-show/improv-drop-ins-3-2-2-3-3-2/2026-07-13/",
      "description": ""
    },
    {
      "date": "2026-07-17",
      "title": "This Is Your Musical",
      "venue": "Bristol Improv Theatre",
      "time": "21:00–23:00",
      "type": "show",
      "url": "https://improvtheatre.co.uk/upcoming-show/this-is-your-musical-2026/2026-07-17/",
      "description": ""
    },
    {
      "date": "2026-07-20",
      "title": "Lunchtime Improv with Rebecca MacMillan",
      "venue": "Bristol Improv Theatre",
      "time": "14:00–15:30",
      "type": "drop-in",
      "url": "https://improvtheatre.co.uk/upcoming-show/lunchtime-improv-with-rebecca-macmillan-2-2/2026-07-20/",
      "description": ""
    },
    {
      "date": "2026-07-20",
      "title": "Improv Drop-ins",
      "venue": "Bristol Improv Theatre",
      "time": "20:00–22:00",
      "type": "drop-in",
      "url": "https://improvtheatre.co.uk/upcoming-show/improv-drop-ins-3-2-2-3-3-2/2026-07-20/",
      "description": ""
    },
    {
      "date": "2026-07-25",
      "title": "Improv Taster Session",
      "venue": "Bristol Improv Theatre",
      "time": "15:00–17:00",
      "type": "drop-in",
      "url": "https://improvtheatre.co.uk/upcoming-show/improv-taster-session-3-2/2026-07-25/",
      "description": ""
    },
    {
      "date": "2026-07-27",
      "title": "Lunchtime Improv with Rebecca MacMillan",
      "venue": "Bristol Improv Theatre",
      "time": "14:00–15:30",
      "type": "drop-in",
      "url": "https://improvtheatre.co.uk/upcoming-show/lunchtime-improv-with-rebecca-macmillan-2-2/2026-07-27/",
      "description": ""
    },
    {
      "date": "2026-07-27",
      "title": "Improv Drop-ins",
      "venue": "Bristol Improv Theatre",
      "time": "20:00–22:00",
      "type": "drop-in",
      "url": "https://improvtheatre.co.uk/upcoming-show/improv-drop-ins-3-2-2-3-3-2/2026-07-27/",
      "description": ""
    },
    {
      "date": "2026-08-03",
      "title": "Lunchtime Improv with Rebecca MacMillan",
      "venue": "Bristol Improv Theatre",
      "time": "14:00–15:30",
      "type": "drop-in",
      "url": "https://improvtheatre.co.uk/upcoming-show/lunchtime-improv-with-rebecca-macmillan-2-2/2026-08-03/",
      "description": ""
    },
    {
      "date": "2026-08-03",
      "title": "Improv Drop-ins",
      "venue": "Bristol Improv Theatre",
      "time": "20:00–22:00",
      "type": "drop-in",
      "url": "https://improvtheatre.co.uk/upcoming-show/improv-drop-ins-3-2-2-3-3-2/2026-08-03/",
      "description": ""
    },
    {
      "date": "2026-08-07",
      "title": "The Bish Bosh Bash: The Improvised Game Show",
      "venue": "Bristol Improv Theatre",
      "time": "20:30–22:30",
      "type": "show",
      "url": "https://improvtheatre.co.uk/upcoming-show/the-bish-bosh-bash-the-improvised-game-show-2026/2026-08-07/",
      "description": ""
    },
    {
      "date": "2026-08-08",
      "title": "Improv Taster Session",
      "venue": "Bristol Improv Theatre",
      "time": "15:00–17:00",
      "type": "drop-in",
      "url": "https://improvtheatre.co.uk/upcoming-show/improv-taster-session-3-2-4/",
      "description": ""
    },
    {
      "date": "2026-08-10",
      "title": "Lunchtime Improv with Rebecca MacMillan",
      "venue": "Bristol Improv Theatre",
      "time": "14:00–15:30",
      "type": "drop-in",
      "url": "https://improvtheatre.co.uk/upcoming-show/lunchtime-improv-with-rebecca-macmillan-2-2/2026-08-10/",
      "description": ""
    },
    {
      "date": "2026-08-10",
      "title": "Improv Drop-ins",
      "venue": "Bristol Improv Theatre",
      "time": "20:00–22:00",
      "type": "drop-in",
      "url": "https://improvtheatre.co.uk/upcoming-show/improv-drop-ins-3-2-2-3-3-2/2026-08-10/",
      "description": ""
    },
    {
      "date": "2026-08-14",
      "title": "This Is Your Musical",
      "venue": "Bristol Improv Theatre",
      "time": "21:00–23:00",
      "type": "show",
      "url": "https://improvtheatre.co.uk/upcoming-show/this-is-your-musical-2026/2026-08-14/",
      "description": ""
    },
    {
      "date": "2026-08-17",
      "title": "Lunchtime Improv with Rebecca MacMillan",
      "venue": "Bristol Improv Theatre",
      "time": "14:00–15:30",
      "type": "drop-in",
      "url": "https://improvtheatre.co.uk/upcoming-show/lunchtime-improv-with-rebecca-macmillan-2-2/2026-08-17/",
      "description": ""
    },
    {
      "date": "2026-08-17",
      "title": "Improv Drop-ins",
      "venue": "Bristol Improv Theatre",
      "time": "20:00–22:00",
      "type": "drop-in",
      "url": "https://improvtheatre.co.uk/upcoming-show/improv-drop-ins-3-2-2-3-3-2/2026-08-17/",
      "description": ""
    },
    {
      "date": "2026-08-22",
      "title": "Improv Taster Session",
      "venue": "Bristol Improv Theatre",
      "time": "15:00–17:00",
      "type": "drop-in",
      "url": "https://improvtheatre.co.uk/upcoming-show/improv-taster-session-3-2/2026-08-22/",
      "description": ""
    },
    {
      "date": "2026-08-22",
      "title": "LGBTQ+ Improv Drop-In",
      "venue": "Bristol Improv Theatre",
      "time": "15:00–17:00",
      "type": "drop-in",
      "url": "https://improvtheatre.co.uk/upcoming-show/lgbtq-improv-drop-in-3-2/2026-08-22/",
      "description": ""
    },
    {
      "date": "2026-08-24",
      "title": "Lunchtime Improv with Rebecca MacMillan",
      "venue": "Bristol Improv Theatre",
      "time": "14:00–15:30",
      "type": "drop-in",
      "url": "https://improvtheatre.co.uk/upcoming-show/lunchtime-improv-with-rebecca-macmillan-2-2/2026-08-24/",
      "description": ""
    },
    {
      "date": "2026-08-24",
      "title": "Improv Drop-ins",
      "venue": "Bristol Improv Theatre",
      "time": "20:00–22:00",
      "type": "drop-in",
      "url": "https://improvtheatre.co.uk/upcoming-show/improv-drop-ins-3-2-2-3-3-2/2026-08-24/",
      "description": ""
    },
    {
      "date": "2026-08-31",
      "title": "Lunchtime Improv with Rebecca MacMillan",
      "venue": "Bristol Improv Theatre",
      "time": "14:00–15:30",
      "type": "drop-in",
      "url": "https://improvtheatre.co.uk/upcoming-show/lunchtime-improv-with-rebecca-macmillan-2-2/2026-08-31/",
      "description": ""
    },
    {
      "date": "2026-08-31",
      "title": "Improv Drop-ins",
      "venue": "Bristol Improv Theatre",
      "time": "20:00–22:00",
      "type": "drop-in",
      "url": "https://improvtheatre.co.uk/upcoming-show/improv-drop-ins-3-2-2-3-3-2/2026-08-31/",
      "description": ""
    },
    {
      "date": "2026-09-04",
      "title": "The Bish Bosh Bash: The Improvised Game Show",
      "venue": "Bristol Improv Theatre",
      "time": "20:30–22:30",
      "type": "show",
      "url": "https://improvtheatre.co.uk/upcoming-show/the-bish-bosh-bash-the-improvised-game-show-2026/2026-09-04/",
      "description": ""
    },
    {
      "date": "2026-09-07",
      "title": "Improv Drop-ins",
      "venue": "Bristol Improv Theatre",
      "time": "20:00–22:00",
      "type": "drop-in",
      "url": "https://improvtheatre.co.uk/upcoming-show/improv-drop-ins-3-2-2-3-3-2/2026-09-07/",
      "description": ""
    },
    {
      "date": "2026-09-12",
      "title": "Improv Taster Session",
      "venue": "Bristol Improv Theatre",
      "time": "15:00–17:00",
      "type": "drop-in",
      "url": "https://improvtheatre.co.uk/upcoming-show/improv-taster-session-3-2/2026-09-12/",
      "description": ""
    },
    {
      "date": "2026-09-14",
      "title": "Improv Drop-ins",
      "venue": "Bristol Improv Theatre",
      "time": "20:00–22:00",
      "type": "drop-in",
      "url": "https://improvtheatre.co.uk/upcoming-show/improv-drop-ins-3-2-2-3-3-2/2026-09-14/",
      "description": ""
    },
    {
      "date": "2026-09-16",
      "title": "Murder, She Didn’t Write",
      "venue": "Bristol Old Vic",
      "time": "20:30",
      "type": "show",
      "url": "https://bristololdvic.org.uk/whats-on/murder-she-didnt-write-1",
      "description": ""
    },
    {
      "date": "2026-09-17",
      "title": "Murder, She Didn’t Write",
      "venue": "Bristol Old Vic",
      "time": "20:30",
      "type": "show",
      "url": "https://bristololdvic.org.uk/whats-on/murder-she-didnt-write-1",
      "description": ""
    },
    {
      "date": "2026-09-18",
      "title": "Murder, She Didn’t Write",
      "venue": "Bristol Old Vic",
      "time": "20:30",
      "type": "show",
      "url": "https://bristololdvic.org.uk/whats-on/murder-she-didnt-write-1",
      "description": ""
    },
    {
      "date": "2026-09-18",
      "title": "This Is Your Musical",
      "venue": "Bristol Improv Theatre",
      "time": "21:00–23:00",
      "type": "show",
      "url": "https://improvtheatre.co.uk/upcoming-show/this-is-your-musical-2026/2026-09-18/",
      "description": ""
    },
    {
      "date": "2026-09-19",
      "title": "Murder, She Didn’t Write",
      "venue": "Bristol Old Vic",
      "time": "20:30",
      "type": "show",
      "url": "https://bristololdvic.org.uk/whats-on/murder-she-didnt-write-1",
      "description": ""
    },
    {
      "date": "2026-09-21",
      "title": "Improv Drop-ins",
      "venue": "Bristol Improv Theatre",
      "time": "20:00–22:00",
      "type": "drop-in",
      "url": "https://improvtheatre.co.uk/upcoming-show/improv-drop-ins-3-2-2-3-3-2/2026-09-21/",
      "description": ""
    },
    {
      "date": "2026-09-26",
      "title": "Improv Taster Session",
      "venue": "Bristol Improv Theatre",
      "time": "15:00–17:00",
      "type": "drop-in",
      "url": "https://improvtheatre.co.uk/upcoming-show/improv-taster-session-3-2/2026-09-26/",
      "description": ""
    },
    {
      "date": "2026-09-28",
      "title": "Improv Drop-ins",
      "venue": "Bristol Improv Theatre",
      "time": "20:00–22:00",
      "type": "drop-in",
      "url": "https://improvtheatre.co.uk/upcoming-show/improv-drop-ins-3-2-2-3-3-2/2026-09-28/",
      "description": ""
    },
    {
      "date": "2026-10-02",
      "title": "The Bish Bosh Bash: The Improvised Game Show",
      "venue": "Bristol Improv Theatre",
      "time": "20:30–22:30",
      "type": "show",
      "url": "https://improvtheatre.co.uk/upcoming-show/the-bish-bosh-bash-the-improvised-game-show-2026/2026-10-02/",
      "description": ""
    },
    {
      "date": "2026-10-05",
      "title": "Improv Drop-ins",
      "venue": "Bristol Improv Theatre",
      "time": "20:00–22:00",
      "type": "drop-in",
      "url": "https://improvtheatre.co.uk/upcoming-show/improv-drop-ins-3-2-2-3-3-2/2026-10-05/",
      "description": ""
    },
    {
      "date": "2026-10-10",
      "title": "Improv Taster Session",
      "venue": "Bristol Improv Theatre",
      "time": "15:00–17:00",
      "type": "drop-in",
      "url": "https://improvtheatre.co.uk/upcoming-show/improv-taster-session-3-2/2026-10-10/",
      "description": ""
    },
    {
      "date": "2026-10-10",
      "title": "LGBTQ+ Improv Drop-In",
      "venue": "Bristol Improv Theatre",
      "time": "15:00–17:00",
      "type": "drop-in",
      "url": "https://improvtheatre.co.uk/upcoming-show/lgbtq-improv-drop-in-3-2/2026-10-10/",
      "description": ""
    },
    {
      "date": "2026-10-12",
      "title": "Improv Drop-ins",
      "venue": "Bristol Improv Theatre",
      "time": "20:00–22:00",
      "type": "drop-in",
      "url": "https://improvtheatre.co.uk/upcoming-show/improv-drop-ins-3-2-2-3-3-2/2026-10-12/",
      "description": ""
    },
    {
      "date": "2026-10-16",
      "title": "This Is Your Musical",
      "venue": "Bristol Improv Theatre",
      "time": "21:00–23:00",
      "type": "show",
      "url": "https://improvtheatre.co.uk/upcoming-show/this-is-your-musical-2026/2026-10-16/",
      "description": ""
    },
    {
      "date": "2026-10-19",
      "title": "Improv Drop-ins",
      "venue": "Bristol Improv Theatre",
      "time": "20:00–22:00",
      "type": "drop-in",
      "url": "https://improvtheatre.co.uk/upcoming-show/improv-drop-ins-3-2-2-3-3-2/2026-10-19/",
      "description": ""
    },
    {
      "date": "2026-10-26",
      "title": "Improv Drop-ins",
      "venue": "Bristol Improv Theatre",
      "time": "19:00–21:00",
      "type": "drop-in",
      "url": "https://improvtheatre.co.uk/upcoming-show/improv-drop-ins-3-2-2-3-3-2/2026-10-26/",
      "description": ""
    },
    {
      "date": "2026-10-31",
      "title": "Improv Taster Session",
      "venue": "Bristol Improv Theatre",
      "time": "14:00–16:00",
      "type": "drop-in",
      "url": "https://improvtheatre.co.uk/upcoming-show/improv-taster-session-3-2/2026-10-31/",
      "description": ""
    },
    {
      "date": "2026-11-02",
      "title": "Improv Drop-ins",
      "venue": "Bristol Improv Theatre",
      "time": "19:00–21:00",
      "type": "drop-in",
      "url": "https://improvtheatre.co.uk/upcoming-show/improv-drop-ins-3-2-2-3-3-2/2026-11-02/",
      "description": ""
    },
    {
      "date": "2026-11-09",
      "title": "Improv Drop-ins",
      "venue": "Bristol Improv Theatre",
      "time": "19:00–21:00",
      "type": "drop-in",
      "url": "https://improvtheatre.co.uk/upcoming-show/improv-drop-ins-3-2-2-3-3-2/2026-11-09/",
      "description": ""
    },
    {
      "date": "2026-11-14",
      "title": "Improv Taster Session",
      "venue": "Bristol Improv Theatre",
      "time": "14:00–16:00",
      "type": "drop-in",
      "url": "https://improvtheatre.co.uk/upcoming-show/improv-taster-session-3-2/2026-11-14/",
      "description": ""
    },
    {
      "date": "2026-11-16",
      "title": "Improv Drop-ins",
      "venue": "Bristol Improv Theatre",
      "time": "19:00–21:00",
      "type": "drop-in",
      "url": "https://improvtheatre.co.uk/upcoming-show/improv-drop-ins-3-2-2-3-3-2/2026-11-16/",
      "description": ""
    },
    {
      "date": "2026-11-20",
      "title": "This Is Your Musical",
      "venue": "Bristol Improv Theatre",
      "time": "20:00–22:00",
      "type": "show",
      "url": "https://improvtheatre.co.uk/upcoming-show/this-is-your-musical-2026/2026-11-20/",
      "description": ""
    },
    {
      "date": "2026-11-23",
      "title": "Improv Drop-ins",
      "venue": "Bristol Improv Theatre",
      "time": "19:00–21:00",
      "type": "drop-in",
      "url": "https://improvtheatre.co.uk/upcoming-show/improv-drop-ins-3-2-2-3-3-2/2026-11-23/",
      "description": ""
    },
    {
      "date": "2026-11-28",
      "title": "Improv Taster Session",
      "venue": "Bristol Improv Theatre",
      "time": "14:00–16:00",
      "type": "drop-in",
      "url": "https://improvtheatre.co.uk/upcoming-show/improv-taster-session-3-2/2026-11-28/",
      "description": ""
    },
    {
      "date": "2026-11-30",
      "title": "Improv Drop-ins",
      "venue": "Bristol Improv Theatre",
      "time": "19:00–21:00",
      "type": "drop-in",
      "url": "https://improvtheatre.co.uk/upcoming-show/improv-drop-ins-3-2-2-3-3-2/2026-11-30/",
      "description": ""
    },
    {
      "date": "2026-12-04",
      "title": "The Bish Bosh Bash: The Improvised Game Show",
      "venue": "Bristol Improv Theatre",
      "time": "19:30–21:30",
      "type": "show",
      "url": "https://improvtheatre.co.uk/upcoming-show/the-bish-bosh-bash-the-improvised-game-show-2026/2026-12-04/",
      "description": ""
    },
    {
      "date": "2026-12-07",
      "title": "Improv Drop-ins",
      "venue": "Bristol Improv Theatre",
      "time": "19:00–21:00",
      "type": "drop-in",
      "url": "https://improvtheatre.co.uk/upcoming-show/improv-drop-ins-3-2-2-3-3-2/2026-12-07/",
      "description": ""
    },
    {
      "date": "2026-12-12",
      "title": "Improv Taster Session",
      "venue": "Bristol Improv Theatre",
      "time": "14:00–16:00",
      "type": "drop-in",
      "url": "https://improvtheatre.co.uk/upcoming-show/improv-taster-session-3-2/2026-12-12/",
      "description": ""
    },
    {
      "date": "2026-12-12",
      "title": "LGBTQ+ Improv Drop-In",
      "venue": "Bristol Improv Theatre",
      "time": "14:00–16:00",
      "type": "drop-in",
      "url": "https://improvtheatre.co.uk/upcoming-show/lgbtq-improv-drop-in-3-2/2026-12-12/",
      "description": ""
    },
    {
      "date": "2026-12-12",
      "title": "This Is Your Musical",
      "venue": "Bristol Improv Theatre",
      "time": "20:00–22:00",
      "type": "show",
      "url": "https://improvtheatre.co.uk/upcoming-show/this-is-your-musical-2026/2026-12-12/",
      "description": ""
    },
    {
      "date": "2026-12-14",
      "title": "Improv Drop-ins",
      "venue": "Bristol Improv Theatre",
      "time": "19:00–21:00",
      "type": "drop-in",
      "url": "https://improvtheatre.co.uk/upcoming-show/improv-drop-ins-3-2-2-3-3-2/2026-12-14/",
      "description": ""
    },
    {
      "date": "2026-12-21",
      "title": "Improv Drop-ins",
      "venue": "Bristol Improv Theatre",
      "time": "19:00–21:00",
      "type": "drop-in",
      "url": "https://improvtheatre.co.uk/upcoming-show/improv-drop-ins-3-2-2-3-3-2/2026-12-21/",
      "description": ""
    },
    {
      "date": "2026-12-28",
      "title": "Improv Drop-ins",
      "venue": "Bristol Improv Theatre",
      "time": "19:00–21:00",
      "type": "drop-in",
      "url": "https://improvtheatre.co.uk/upcoming-show/improv-drop-ins-3-2-2-3-3-2/2026-12-28/",
      "description": ""
    },
    {
      "date": "2027-02-09",
      "title": "Closer Each Day: The Improvised Soap Opera",
      "venue": "Wardrobe Theatre",
      "time": "19:30",
      "type": "show",
      "url": "https://thewardrobetheatre.com/shows/closer-each-day/",
      "description": ""
    },
    {
      "date": "2027-02-11",
      "title": "The Bish Bosh Bash: The Improvised Game Show",
      "venue": "Bristol Improv Theatre",
      "time": "19:30–21:30",
      "type": "show",
      "url": "https://improvtheatre.co.uk/upcoming-show/the-bish-bosh-bash-the-improvised-game-show-2026/2027-02-11/",
      "description": ""
    }
  ]
}